Metadata-Version: 2.1
Name: ai1wm
Version: 1.2.3
Summary: Packs/Unpacks `All-in-One WP Migration` packages
Home-page: https://github.com/sanderwang/ai1wm
Author: Sander Wang
Author-email: sw.online@outlook.com
License: MIT
Download-URL: https://github.com/sanderwang/ai1wm/archive/1.2.3.tar.gz
Keywords: WordPress,All-in-One WP Migration
Platform: UNKNOWN
Classifier: Development Status :: 5 - Production/Stable
Classifier: Intended Audience :: Developers
Classifier: Topic :: Software Development :: Build Tools
Classifier: License :: OSI Approved :: MIT License
Classifier: Programming Language :: Python :: 2
Classifier: Programming Language :: Python :: 2.7
Classifier: Programming Language :: Python :: 3
Classifier: Programming Language :: Python :: 3.4
Classifier: Programming Language :: Python :: 3.5
Classifier: Programming Language :: Python :: 3.6
Classifier: Programming Language :: Python :: 3.7
Classifier: Programming Language :: Python :: 3.8
